{
    "textures": {
        "0": "blocks/planks_oak",
        "1": "blocks/stone",
        "2": "blocks/wool_colored_red"
    },
    "elements": [
        {
            "name": "Top",
            "from": [ 0.0, 31.0, 0.0 ], 
            "to": [ 16.0, 32.0, 16.0 ], 
            "faces": {
                "north": { "texture": "#0", "uv": [ 0.0, 0.0, 16.0, 1.0 ] },
                "east": { "texture": "#0", "uv": [ 0.0, 0.0, 16.0, 1.0 ] },
                "south": { "texture": "#0", "uv": [ 0.0, 0.0, 16.0, 1.0 ] },
                "west": { "texture": "#0", "uv": [ 0.0, 0.0, 16.0, 1.0 ] },
                "up": { "texture": "#0", "uv": [ 0.0, 0.0, 16.0, 16.0 ] },
                "down": { "texture": "#0", "uv": [ 0.0, 0.0, 16.0, 16.0 ] }
            }
        },
        {
            "name": "Right",
            "from": [ 15.0, 0.0, 1.0 ], 
            "to": [ 16.0, 16.0, 16.0 ], 
            "faces": {
                "east": { "texture": "#0", "uv": [ 0.0, 0.0, 15.0, 16.0 ] },
                "south": { "texture": "#0", "uv": [ 0.0, 0.0, 1.0, 16.0 ] },
                "west": { "texture": "#0", "uv": [ 0.0, 0.0, 15.0, 16.0 ] },
                "down": { "texture": "#0", "uv": [ 0.0, 0.0, 1.0, 15.0 ] }
            }
        },
        {
            "name": "Right2",
            "from": [ 15.0, 16.0, 1.0 ], 
            "to": [ 16.0, 31.0, 16.0 ], 
            "faces": {
                "east": { "texture": "#0", "uv": [ 0.0, 1.0, 15.0, 16.0 ] },
                "south": { "texture": "#0", "uv": [ 0.0, 1.0, 1.0, 16.0 ] },
                "west": { "texture": "#0", "uv": [ 0.0, 1.0, 15.0, 16.0 ] }
            }
        },
        {
            "name": "Left",
            "from": [ 0.0, 0.0, 1.0 ], 
            "to": [ 1.0, 16.0, 16.0 ], 
            "faces": {
                "east": { "texture": "#0", "uv": [ 0.0, 0.0, 15.0, 16.0 ] },
                "south": { "texture": "#0", "uv": [ 0.0, 0.0, 1.0, 16.0 ] },
                "west": { "texture": "#0", "uv": [ 0.0, 0.0, 15.0, 16.0 ] },
                "down": { "texture": "#0", "uv": [ 0.0, 0.0, 1.0, 15.0 ] }
            }
        },
        {
            "name": "Left2",
            "from": [ 0.0, 16.0, 1.0 ], 
            "to": [ 1.0, 31.0, 16.0 ], 
            "faces": {
                "east": { "texture": "#0", "uv": [ 0.0, 1.0, 15.0, 16.0 ] },
                "south": { "texture": "#0", "uv": [ 0.0, 1.0, 1.0, 16.0 ] },
                "west": { "texture": "#0", "uv": [ 0.0, 1.0, 15.0, 16.0 ] }
            }
        },
        {
            "name": "Back",
            "from": [ 0.0, 0.0, 0.0 ], 
            "to": [ 16.0, 16.0, 1.0 ], 
            "faces": {
                "north": { "texture": "#0", "uv": [ 0.0, 0.0, 16.0, 16.0 ] },
                "east": { "texture": "#0", "uv": [ 0.0, 0.0, 1.0, 16.0 ] },
                "south": { "texture": "#0", "uv": [ 0.0, 0.0, 16.0, 16.0 ] },
                "west": { "texture": "#0", "uv": [ 0.0, 0.0, 1.0, 16.0 ] },
                "down": { "texture": "#0", "uv": [ 0.0, 0.0, 16.0, 1.0 ] }
            }
        },
        {
            "name": "Back2",
            "from": [ 0.0, 16.0, 0.0 ], 
            "to": [ 16.0, 31.0, 1.0 ], 
            "faces": {
                "north": { "texture": "#0", "uv": [ 0.0, 1.0, 16.0, 16.0 ] },
                "east": { "texture": "#0", "uv": [ 0.0, 1.0, 1.0, 16.0 ] },
                "south": { "texture": "#0", "uv": [ 0.0, 1.0, 16.0, 16.0 ] },
                "west": { "texture": "#0", "uv": [ 0.0, 1.0, 1.0, 16.0 ] }
            }
        },
        {
            "name": "Pole",
            "from": [ 1.0, 28.0, 15.0 ], 
            "to": [ 15.0, 29.0, 16.0 ], 
            "rotation": { "origin": [ 8.0, 28.0, 15.0 ], "axis": "x", "angle": -45.0 },
            "faces": {
                "north": { "texture": "#1", "uv": [ 0.0, 1.0, 14.0, 2.0 ] },
                "south": { "texture": "#1", "uv": [ 0.0, 1.0, 14.0, 2.0 ] },
                "up": { "texture": "#1", "uv": [ 0.0, 0.0, 14.0, 1.0 ] },
                "down": { "texture": "#1", "uv": [ 0.0, 0.0, 14.0, 1.0 ] }
            }
        },
        {
            "name": "Curtain_1",
            "from": [ 1.0, 14.0, 14.49999999254942 ], 
            "to": [ 3.0, 28.0, 15.49999999254942 ], 
            "faces": {
                "east": { "texture": "#2", "uv": [ 0.0, 0.0, 1.0, 14.0 ] },
                "south": { "texture": "#2", "uv": [ 0.0, 0.0, 2.0, 14.0 ] },
                "west": { "texture": "#2", "uv": [ 0.0, 0.0, 1.0, 14.0 ] },
                "up": { "texture": "#2", "uv": [ 0.0, 0.0, 2.0, 1.0 ] }
            }
        },
        {
            "name": "Curtain_1b",
            "from": [ 1.0, 0.0, 14.49999999254942 ], 
            "to": [ 3.0, 14.0, 15.49999999254942 ], 
            "faces": {
                "east": { "texture": "#2", "uv": [ 0.0, 2.0, 1.0, 16.0 ] },
                "south": { "texture": "#2", "uv": [ 0.0, 2.0, 2.0, 16.0 ] },
                "west": { "texture": "#2", "uv": [ 0.0, 2.0, 1.0, 16.0 ] },
                "up": { "texture": "#2", "uv": [ 0.0, 0.0, 2.0, 1.0 ] }
            }
        },
        {
            "name": "Curtain_2",
            "from": [ 1.0, 14.0, 13.49999999254942 ], 
            "to": [ 5.0, 28.0, 14.49999999254942 ], 
            "faces": {
                "east": { "texture": "#2", "uv": [ 0.0, 0.0, 1.0, 14.0 ] },
                "south": { "texture": "#2", "uv": [ 0.0, 0.0, 2.0, 14.0 ] },
                "west": { "texture": "#2", "uv": [ 0.0, 0.0, 1.0, 14.0 ] },
                "up": { "texture": "#2", "uv": [ 0.0, 0.0, 2.0, 1.0 ] }
            }
        },
        {
            "name": "Curtain_2b",
            "from": [ 3.0, 0.0, 13.49999999254942 ], 
            "to": [ 5.0, 14.0, 14.49999999254942 ], 
            "faces": {
                "east": { "texture": "#2", "uv": [ 0.0, 2.0, 1.0, 16.0 ] },
                "south": { "texture": "#2", "uv": [ 0.0, 2.0, 2.0, 16.0 ] },
                "west": { "texture": "#2", "uv": [ 0.0, 2.0, 1.0, 16.0 ] },
                "up": { "texture": "#2", "uv": [ 0.0, 0.0, 2.0, 1.0 ] }
            }
        },
        {
            "name": "Curtain_3",
            "from": [ 5.0, 14.0, 14.49999999254942 ], 
            "to": [ 7.0, 28.0, 15.49999999254942 ], 
            "faces": {
                "east": { "texture": "#2", "uv": [ 0.0, 0.0, 1.0, 14.0 ] },
                "south": { "texture": "#2", "uv": [ 0.0, 0.0, 2.0, 14.0 ] },
                "west": { "texture": "#2", "uv": [ 0.0, 0.0, 1.0, 14.0 ] },
                "up": { "texture": "#2", "uv": [ 0.0, 0.0, 2.0, 1.0 ] }
            }
        },
        {
            "name": "Curtain_3b",
            "from": [ 5.0, 0.0, 14.49999999254942 ], 
            "to": [ 7.0, 14.0, 15.49999999254942 ], 
            "faces": {
                "east": { "texture": "#2", "uv": [ 0.0, 2.0, 1.0, 16.0 ] },
                "south": { "texture": "#2", "uv": [ 0.0, 2.0, 2.0, 16.0 ] },
                "west": { "texture": "#2", "uv": [ 0.0, 2.0, 1.0, 16.0 ] },
                "up": { "texture": "#2", "uv": [ 0.0, 0.0, 2.0, 1.0 ] }
            }
        },
        {
            "name": "Curtain_4",
            "from": [ 5.0, 14.0, 13.49999999254942 ], 
            "to": [ 9.0, 28.0, 14.49999999254942 ], 
            "faces": {
                "east": { "texture": "#2", "uv": [ 0.0, 0.0, 1.0, 14.0 ] },
                "south": { "texture": "#2", "uv": [ 0.0, 0.0, 2.0, 14.0 ] },
                "west": { "texture": "#2", "uv": [ 0.0, 0.0, 1.0, 14.0 ] },
                "up": { "texture": "#2", "uv": [ 0.0, 0.0, 2.0, 1.0 ] }
            }
        },
        {
            "name": "Curtain_4b",
            "from": [ 7.0, 0.0, 13.49999999254942 ], 
            "to": [ 9.0, 14.0, 14.49999999254942 ], 
            "faces": {
                "east": { "texture": "#2", "uv": [ 0.0, 2.0, 1.0, 16.0 ] },
                "south": { "texture": "#2", "uv": [ 0.0, 2.0, 2.0, 16.0 ] },
                "west": { "texture": "#2", "uv": [ 0.0, 2.0, 1.0, 16.0 ] },
                "up": { "texture": "#2", "uv": [ 0.0, 0.0, 2.0, 1.0 ] }
            }
        },
        {
            "name": "Curtain_5",
            "from": [ 9.0, 14.0, 14.49999999254942 ], 
            "to": [ 11.0, 28.0, 15.49999999254942 ], 
            "faces": {
                "east": { "texture": "#2", "uv": [ 0.0, 0.0, 1.0, 14.0 ] },
                "south": { "texture": "#2", "uv": [ 0.0, 0.0, 2.0, 14.0 ] },
                "west": { "texture": "#2", "uv": [ 0.0, 0.0, 1.0, 14.0 ] },
                "up": { "texture": "#2", "uv": [ 0.0, 0.0, 2.0, 1.0 ] }
            }
        },
        {
            "name": "Curtain_5b",
            "from": [ 9.0, 0.0, 14.49999999254942 ], 
            "to": [ 11.0, 14.0, 15.49999999254942 ], 
            "faces": {
                "east": { "texture": "#2", "uv": [ 0.0, 2.0, 1.0, 16.0 ] },
                "south": { "texture": "#2", "uv": [ 0.0, 2.0, 2.0, 16.0 ] },
                "west": { "texture": "#2", "uv": [ 0.0, 2.0, 1.0, 16.0 ] },
                "up": { "texture": "#2", "uv": [ 0.0, 0.0, 2.0, 1.0 ] }
            }
        },
        {
            "name": "Curtain_6",
            "from": [ 9.0, 14.0, 13.49999999254942 ], 
            "to": [ 13.0, 28.0, 14.49999999254942 ], 
            "faces": {
                "east": { "texture": "#2", "uv": [ 0.0, 0.0, 1.0, 14.0 ] },
                "south": { "texture": "#2", "uv": [ 0.0, 0.0, 2.0, 14.0 ] },
                "west": { "texture": "#2", "uv": [ 0.0, 0.0, 1.0, 14.0 ] },
                "up": { "texture": "#2", "uv": [ 0.0, 0.0, 2.0, 1.0 ] }
            }
        },
        {
            "name": "Curtain_6b",
            "from": [ 11.0, 0.0, 13.49999999254942 ], 
            "to": [ 13.0, 14.0, 14.49999999254942 ], 
            "faces": {
                "east": { "texture": "#2", "uv": [ 0.0, 2.0, 1.0, 16.0 ] },
                "south": { "texture": "#2", "uv": [ 0.0, 2.0, 2.0, 16.0 ] },
                "west": { "texture": "#2", "uv": [ 0.0, 2.0, 1.0, 16.0 ] },
                "up": { "texture": "#2", "uv": [ 0.0, 0.0, 2.0, 1.0 ] }
            }
        },
        {
            "name": "Curtain_7",
            "from": [ 13.0, 14.0, 14.49999999254942 ], 
            "to": [ 15.0, 28.0, 15.49999999254942 ], 
            "faces": {
                "east": { "texture": "#2", "uv": [ 0.0, 0.0, 1.0, 14.0 ] },
                "south": { "texture": "#2", "uv": [ 0.0, 0.0, 2.0, 14.0 ] },
                "west": { "texture": "#2", "uv": [ 0.0, 0.0, 1.0, 14.0 ] },
                "up": { "texture": "#2", "uv": [ 0.0, 0.0, 2.0, 1.0 ] }
            }
        },
        {
            "name": "Curtain_7b",
            "from": [ 13.0, 0.0, 14.49999999254942 ], 
            "to": [ 15.0, 14.0, 15.49999999254942 ], 
            "faces": {
                "east": { "texture": "#2", "uv": [ 0.0, 2.0, 1.0, 16.0 ] },
                "south": { "texture": "#2", "uv": [ 0.0, 2.0, 2.0, 16.0 ] },
                "west": { "texture": "#2", "uv": [ 0.0, 2.0, 1.0, 16.0 ] },
                "up": { "texture": "#2", "uv": [ 0.0, 0.0, 2.0, 1.0 ] }
            }
        }
    ]
}